l2term/__init__.py
l2term/l2term.py
l2term/multiprocessing.py
l2term-0.0.0.dist-info/METADATA
l2term-0.0.0.dist-info/WHEEL
l2term-0.0.0.dist-info/namespace_packages.txt
l2term-0.0.0.dist-info/top_level.txt
l2term-0.0.0.dist-info/zip-safe
l2term-0.0.0.dist-info/RECORD
